Eitaabot/__init__.py
Eitaabot-1.0.dist-info/METADATA
Eitaabot-1.0.dist-info/WHEEL
Eitaabot-1.0.dist-info/top_level.txt
Eitaabot-1.0.dist-info/RECORD
