Metadata-Version: 2.1
Name: Eitaabot
Version: 1.0
Summary: This is a powerful library for building self robots in Eitaa
Home-page: https://github.com/mrsalari/eitaabot
Author: mohammad saeed salari
Author-email: salari601601@gmail.com
Keywords: eita,eitaapy,tyrobot,pyeitaa,eitaa bot,eitaayar,library eitaa,eitaayar,eitaabot,eitaa-lib,bot,self bot,eitaa.ir,eitaa
Classifier: Programming Language :: Python :: 3.6
Classifier: Programming Language :: Python :: 3.7
Classifier: Programming Language :: Python :: 3.8
Classifier: Programming Language :: Python :: 3.9
Classifier: Programming Language :: Python :: 3.10
Classifier: Programming Language :: Python :: 3.11
Classifier: License :: OSI Approved :: MIT License
Requires-Python: ~=3.7
Requires-Dist: bs4
Requires-Dist: requests
